atap_corpus_loader/CorpusLoader.py
atap_corpus_loader/__init__.py
atap_corpus_loader/controller/Controller.py
atap_corpus_loader/controller/CorpusExportService.py
atap_corpus_loader/controller/GoogleDownloadService.py
atap_corpus_loader/controller/__init__.py
atap_corpus_loader/controller/data_objects/CorpusHeader.py
atap_corpus_loader/controller/data_objects/DataType.py
atap_corpus_loader/controller/data_objects/FileReference.py
atap_corpus_loader/controller/data_objects/HeaderStrategy.py
atap_corpus_loader/controller/data_objects/UniqueNameCorpora.py
atap_corpus_loader/controller/data_objects/ViewCorpusInfo.py
atap_corpus_loader/controller/data_objects/__init__.py
atap_corpus_loader/controller/events/EventManager.py
atap_corpus_loader/controller/events/EventType.py
atap_corpus_loader/controller/events/__init__.py
atap_corpus_loader/controller/loader_service/FileLoadError.py
atap_corpus_loader/controller/loader_service/FileLoaderService.py
atap_corpus_loader/controller/loader_service/LoaderService.py
atap_corpus_loader/controller/loader_service/OniLoaderService.py
atap_corpus_loader/controller/loader_service/__init__.py
atap_corpus_loader/controller/loader_service/file_loader_strategy/FileLoaderFactory.py
atap_corpus_loader/controller/loader_service/file_loader_strategy/FileLoaderStrategy.py
atap_corpus_loader/controller/loader_service/file_loader_strategy/__init__.py
atap_corpus_loader/controller/loader_service/file_loader_strategy/concrete_strategies/CSVLoaderStrategy.py
atap_corpus_loader/controller/loader_service/file_loader_strategy/concrete_strategies/DOCXLoaderStrategy.py
atap_corpus_loader/controller/loader_service/file_loader_strategy/concrete_strategies/ODSLoaderStrategy.py
atap_corpus_loader/controller/loader_service/file_loader_strategy/concrete_strategies/ODTLoaderStrategy.py
atap_corpus_loader/controller/loader_service/file_loader_strategy/concrete_strategies/TSVLoaderStrategy.py
atap_corpus_loader-1.8.2.dist-info/LICENSE
atap_corpus_loader-1.8.2.dist-info/METADATA
atap_corpus_loader-1.8.2.dist-info/WHEEL
atap_corpus_loader-1.8.2.dist-info/RECORD
