Metadata-Version: 2.1
Name: atap-corpus-loader
Version: 1.8.2
Summary: A GUI loader for atap_corpus using the Panel library.
Home-page: https://github.com/Australian-Text-Analytics-Platform/atap-corpus-loader
License: MIT
Author: Hamish Croser
Author-email: hamish.croser@sydney.edu.au
Requires-Python: >=3.10,<3.13
Classifier: License :: OSI Approved :: MIT License
Classifier: Programming Language :: Python :: 3
Classifier: Programming Language :: Python :: 3.10
Classifier: Programming Language :: Python :: 3.11
Classifier: Programming Language :: Python :: 3.12
Requires-Dist: XlsxWriter (>=3.2.0,<3.3.0)
Requires-Dist: atap-corpus (>=0.1.15,<0.2.0)
Requires-Dist: gdown (==5.2.0)
Requires-Dist: ipywidgets (>=8.0,<9.0)
Requires-Dist: jupyter_panel_proxy (==0.1.0)
Requires-Dist: odfpy (>=1.4.0,<1.5.0)
Requires-Dist: pandas (>2.0)
Requires-Dist: panel (>=1.4.0,<1.5.0)
Requires-Dist: python-docx (>=1.1.0,<1.2.0)
Project-URL: Documentation, https://australian-text-analytics-platform.github.io/atap-corpus-loader/DOCS.html
Project-URL: Repository, https://github.com/Australian-Text-Analytics-Platform/atap-corpus-loader
